{"AQWiF4NiAkqFdAZeowA4uQ==":"2.1jpg-1900x1069.jpg","0+Bp9qA8GPJ6JXNbuD0mBw==":"3.1jpg-1900x1069.jpg","Ucts9txcPyUhWtEd39H3KQ==":"recurso%202@2x-96x108.png","STx70dhcK0xHTRnOFXfn1A==":"mila_en_el_multiverso_serie_de_tv-452383492-large-770x963.jpg","V0UqTX+D78ejYZDs1bFtxw==":"recurso%202@2x-369x414.png","iL3B0N5JlMsZZ29PJM99FA==":"1.1-1920x1080.jpg","Eb/U4VhTrZf2oDs28/ICkg==":"3.1jpg-1432x806.jpg","1d6PP+Uswwo4kJmBooUGhQ==":"3.1jpg-1432x806.jpeg","TGTlXAPNbhzHpUzJcU574A==":"2.1jpg-1920x1080.jpg","JauTDLNiUleld91IdVibfQ==":"3.1jpg-1920x1080.jpg","9y75p/8GrsHFJp40eIdfWA==":"1-600x600.png","z95yExqbp4YAlu4KXgNwOA==":"2-600x600.png","vl7noxy+qxbE6vdj4m28RQ==":"3-600x600.png","pgiSPsRo5HyuSzAqPm27kw==":"4-600x600.png","Tc+hK9aSqhmP4AbO2o343w==":"1-1000x1000.png","+8pOnjrtBmej2/wOlzPMXg==":"1-1-600x600.png","CwbnAliZljGCBUa2DtQgwg==":"2-1-600x600.png","SbZEmF7WXB3OZDz1o2kt6Q==":"3-1-600x600.png","0gudZzlo0slpo3j7oE8teg==":"4-1-600x600.png","RD40kjcNvyh8pMNetBSmEw==":"1-2-600x600.png","FwzxHmz3fBLw16Ad3RnBKQ==":"2-2-600x600.png","B95HilX48SOysWq40lQB7w==":"3-2-600x600.png","4Ngdx6ZP9bBq3JbpXmaowg==":"4-2-600x600.png","p8rrpflYSNiQF8Ze5Zqj9g==":"1-3-600x600.png","vnY5GhVA9MQKXR7eH2vS/w==":"2-3-600x600.png","7hqL/nO107Gxx2bCKybOIA==":"3-3-600x600.png","Ai0mQeKlyLy17TjMLQV+Qg==":"4-3-600x600.png","5tjAHuDTntlJFlU3aulRUQ==":"banner-estatico-sin-texto--1920x540.png","O7bfhx0MbHfAbH/mnO4WRw==":"telefono-538x554.png","5PScGPwa35Fiel0CHgqMag==":"1678930471772-1900x534.png","RQYtNDdpgEKUbHK2pcm7JQ==":"1678930471777-1900x534.png","sTxk7mBOtd/JdyNm9gfbrQ==":"1678930471769-1900x534.png","xiiv3X2s8EvAhPjP4HC7iw==":"1-netflix--240x96.png","gbLqvcQ5/qr+A4kqo8RK1Q==":"2-hbo-240x96.png","SyNdNt+NVzzaiY5bd7yNdw==":"3-start-240x96.png","P6wfwUjoAku/VEtytVPiHQ==":"4-disney-240x96.png","sH8ZfU3Kq/PFwTvnqN8Cdg==":"5-prime-240x96.png","rOsDLuSNk10+TmAuZujOew==":"6-paramount-240x96.png","qdRoEcLdgU8sZ71ALnVbug==":"7-aplee-music-240x96.png","lK2vGOg/aVPWC6SKiKtZOw==":"8-spoty-240x96.png","5TLMrDZ4Ld0O3aEb67DhVA==":"1678942322281.png","iQh/grzmmQQEE3aEkjc9Fw==":"user1.jpg","3RRHfRGCtFEOQaCnKioxDw==":"faceapp-1583810702939.jpg","jSfbJWaHBHvQmXXzXmiYsw==":"user3.jpg"}